{"#include <stdio.h>": 1, "int": 2, "main": 1, "(": 86, ")": 86, "{": 23, "double": 3, "T1": 5, ",": 32, "T2": 5, "Tp": 5, "Tz": 5, "TZ": 5, "Tzb": 3, ";": 84, "B1": 5, "B2": 5, "Bp": 5, "Bz": 5, "BZ": 5, "Bzb": 3, "M1": 5, "M2": 5, "Mp": 5, "Mz": 5, "MZ": 5, "Mzb": 3, "To": 13, "Bo": 14, "Mo": 13, "printf": 40, "\"Unesite bodove za Tarika: \"": 1, "\"\\nI parcijalni ispit: \"": 3, "scanf": 15, "\"%lf\"": 15, "&": 15, "if": 21, "<": 27, "0": 34, "||": 21, ">": 15, "20": 6, "\"Neispravan broj bodova\"": 14, "return": 19, "}": 23, "\"II parcijalni ispit: \"": 3, "\"Prisustvo: \"": 3, "10": 9, "\"Zadace: \"": 3, "\"Zavrsni ispit: \"": 3, "40": 3, "\"Unesite bodove za Bojana: \"": 1, "\"Nesipravan broj bodova\"": 1, "\"Unesite bodove za Mirzu: \"": 1, "=": 6, "+": 15, "5": 3, "/": 3, "6": 24, "&&": 17, "\"Nijedan student nije polozio.\\n\"": 1, "else": 5, ">=": 12, "\"Jedan student je polozio.\\n \"": 1, "\"Dva studenta su polozila.\\n\"": 1, "\"Sva tri studenta su polozila.\\n\"": 1, "==": 5, "\"Sva tri studenta imaju istu ocjenu.\\n\"": 1, "\"Dva od tri studenta imaju istu ocjenu.\\n\"": 1, "\"Svaki student ima razlicitu ocjenu.\\n\"": 1}