{"#include <stdio.h>,int": 1, "int,main": 1, "main,(": 1, "(,)": 1, "),{": 41, "{,double": 1, "double,I1": 1, "I1,,": 1, ",,I2": 1, "I2,,": 1, ",,I3": 1, "I3,,": 1, ",,I4": 1, "I4,,": 1, ",,I5": 1, "I5,,": 1, ",,I6": 1, "I6,,": 1, ",,P1": 1, "P1,,": 1, ",,P2": 1, "P2,,": 1, ",,P3": 1, "P3,,": 1, ",,ZAD1": 1, "ZAD1,,": 1, ",,ZAD2": 1, "ZAD2,,": 1, ",,ZAD3": 1, "ZAD3,,": 1, ",,ZI1": 1, "ZI1,,": 1, ",,ZI2": 1, "ZI2,,": 1, ",,ZI3": 1, "ZI3,,": 1, ",,ZT": 1, "ZT,,": 1, ",,ZM": 1, "ZM,,": 1, ",,ZB": 1, "ZB,;": 1, ";,int": 1, "int,OCT": 1, "OCT,,": 1, ",,OCB": 1, "OCB,,": 1, ",,OCM": 1, "OCM,;": 1, ";,printf": 4, "printf,(": 40, "(,\"Unesite bodove za Tarika: \\n\"": 1, "\"Unesite bodove za Tarika: \\n\",)": 1, "),;": 55, "(,\"I parcijalni ispit: \"": 3, "\"I parcijalni ispit: \",)": 3, ";,scanf": 15, "scanf,(": 15, "(,\"%lf\"": 15, "\"%lf\",,": 15, ",,&": 15, "&,I1": 1, "I1,)": 1, ";,if": 17, "if,(": 40, "(,I1": 1, "I1,<": 1, "<,0": 15, "0,||": 15, "||,I1": 1, "I1,>": 1, ">,20": 6, "20,)": 6, "{,printf": 22, "(,\"Neispravan broj bodova \"": 15, "\"Neispravan broj bodova \",)": 15, ";,return": 15, "return,0": 16, "0,;": 16, ";,}": 40, "},printf": 14, "(,\"II parcijalni ispit: \"": 3, "\"II parcijalni ispit: \",)": 3, "&,I2": 1, "I2,)": 1, "(,I2": 1, "I2,<": 1, "||,I2": 1, "I2,>": 1, "(,\"Prisustvo: \"": 3, "\"Prisustvo: \",)": 3, "&,P1": 1, "P1,)": 1, "(,P1": 1, "P1,<": 1, "||,P1": 1, "P1,>": 1, ">,10": 6, "10,)": 6, "(,\"Zadace: \"": 3, "\"Zadace: \",)": 3, "&,ZAD1": 1, "ZAD1,)": 1, "(,ZAD1": 1, "ZAD1,<": 1, "||,ZAD1": 1, "ZAD1,>": 1, "(,\"Zavrsni ispit: \"": 3, "\"Zavrsni ispit: \",)": 3, "&,ZI1": 1, "ZI1,)": 1, "(,ZI1": 1, "ZI1,<": 1, "||,ZI1": 1, "ZI1,>": 1, ">,40": 3, "40,)": 3, "(,\"Unesite bodove za Bojana: \\n\"": 1, "\"Unesite bodove za Bojana: \\n\",)": 1, "&,I3": 1, "I3,)": 1, "(,I3": 1, "I3,<": 1, "||,I3": 1, "I3,>": 1, "&,I4": 1, "I4,)": 1, "(,I4": 1, "I4,<": 1, "||,I4": 1, "I4,>": 1, "&,P2": 1, "P2,)": 1, "(,P2": 1, "P2,<": 1, "||,P2": 1, "P2,>": 1, "&,ZAD2": 1, "ZAD2,)": 1, "(,ZAD2": 1, "ZAD2,<": 1, "||,ZAD2": 1, "ZAD2,>": 1, "&,ZI2": 1, "ZI2,)": 1, "(,ZI2": 1, "ZI2,<": 1, "||,ZI2": 1, "ZI2,>": 1, "(,\"Unesite bodove za Mirzu: \\n\"": 1, "\"Unesite bodove za Mirzu: \\n\",)": 1, "&,I5": 1, "I5,)": 1, "(,I5": 1, "I5,<": 1, "||,I5": 1, "I5,>": 1, "&,I6": 1, "I6,)": 1, "(,I6": 1, "I6,<": 1, "||,I6": 1, "I6,>": 1, "&,P3": 1, "P3,)": 1, "(,P3": 1, "P3,<": 1, "||,P3": 1, "P3,>": 1, "&,ZAD3": 1, "ZAD3,)": 1, "(,ZAD3": 1, "ZAD3,<": 1, "||,ZAD3": 1, "ZAD3,>": 1, "&,ZI3": 1, "ZI3,)": 1, "(,ZI3": 1, "ZI3,<": 1, "||,ZI3": 1, "ZI3,>": 1, "},ZT": 1, "ZT,=": 1, "=,I1": 1, "I1,+": 1, "+,I2": 1, "I2,+": 1, "+,P1": 1, "P1,+": 1, "+,ZAD1": 1, "ZAD1,+": 1, "+,ZI1": 1, "ZI1,;": 1, ";,ZB": 1, "ZB,=": 1, "=,I3": 1, "I3,+": 1, "+,I4": 1, "I4,+": 1, "+,P2": 1, "P2,+": 1, "+,ZAD2": 1, "ZAD2,+": 1, "+,ZI2": 1, "ZI2,;": 1, ";,ZM": 1, "ZM,=": 1, "=,I5": 1, "I5,+": 1, "+,I6": 1, "I6,+": 1, "+,P3": 1, "P3,+": 1, "+,ZAD3": 1, "ZAD3,+": 1, "+,ZI3": 1, "ZI3,;": 1, "(,ZT": 6, "ZT,<": 1, "<,55": 3, "55,)": 3, "{,OCT": 6, "OCT,=": 6, "=,5": 3, "5,;": 3, "},else": 19, "else,if": 19, "ZT,>=": 5, ">=,55": 3, "55,&&": 3, "&&,ZT": 5, "ZT,<=": 5, "<=,65": 3, "65,)": 3, "=,6": 3, "6,;": 3, ">=,65": 3, "65,&&": 3, "<=,75": 3, "75,)": 3, "=,7": 3, "7,;": 3, ">=,75": 3, "75,&&": 3, "<=,85": 3, "85,)": 3, "=,8": 3, "8,;": 3, ">=,85": 3, "85,&&": 3, "<=,92": 3, "92,)": 3, "=,9": 3, "9,;": 3, ">=,92": 3, "92,&&": 3, "<=,100": 3, "100,)": 3, "=,10": 3, "10,;": 3, "},if": 4, "(,ZB": 6, "ZB,<": 1, "{,OCB": 6, "OCB,=": 6, "ZB,>=": 5, "&&,ZB": 5, "ZB,<=": 5, "(,ZM": 6, "ZM,<": 1, "{,OCM": 6, "OCM,=": 6, "ZM,>=": 5, "&&,ZM": 5, "ZM,<=": 5, "(,OCT": 7, "OCT,<": 5, "<,6": 12, "6,&&": 16, "&&,OCB": 7, "OCB,<": 3, "&&,OCM": 8, "OCM,<": 4, "6,)": 4, "(,\"Nijedan student nije polozio. \\n\"": 1, "\"Nijedan student nije polozio. \\n\",)": 1, "OCT,>=": 3, ">=,6": 12, "6,||": 4, "||,OCB": 2, "OCB,>=": 5, "&&,OCT": 7, "||,OCM": 2, "OCM,>=": 4, "(,\"Jedan student je polozio. \\n\"": 1, "\"Jedan student je polozio. \\n\",)": 1, "(,\"Dva studenta su polozila. \\n\"": 1, "\"Dva studenta su polozila. \\n\",)": 1, "(,\"Sva tri studenta su polozila. \\n\"": 1, "\"Sva tri studenta su polozila. \\n\",)": 1, "OCT,==": 3, "==,OCB": 3, "OCB,&&": 3, "OCM,==": 2, "==,OCT": 1, "OCT,&&": 1, "OCB,)": 2, "(,\"Sva tri studenta imaju istu ocjenu. \\n\"": 1, "\"Sva tri studenta imaju istu ocjenu. \\n\",)": 1, "OCT,!=": 4, "!=,OCM": 3, "OCM,||": 1, "||,OCT": 1, "==,OCM": 1, "OCM,&&": 2, "!=,OCB": 2, "(,\"Dva od tri studenta imaju istu ocjenu. \\n\"": 1, "\"Dva od tri studenta imaju istu ocjenu. \\n\",)": 1, "OCB,!=": 1, "OCM,)": 1, "(,\"Svaki student ima razlicitu ocjenu. \\n\"": 1, "\"Svaki student ima razlicitu ocjenu. \\n\",)": 1, "},}": 1, "},return": 1}