{"#include <stdio.h>,int,main": 1, "int,main,(": 1, "main,(,)": 1, "(,),{": 1, "),{,double": 1, "{,double,T1": 1, "double,T1,,": 1, "T1,,,T2": 1, ",,T2,,": 1, "T2,,,TP": 1, ",,TP,,": 1, "TP,,,TZ": 1, ",,TZ,,": 1, "TZ,,,TZI": 1, ",,TZI,,": 1, "TZI,,,B1": 1, ",,B1,,": 1, "B1,,,B2": 1, ",,B2,,": 1, "B2,,,BP": 1, ",,BP,,": 1, "BP,,,BZ": 1, ",,BZ,,": 1, "BZ,,,BZI": 1, ",,BZI,,": 1, "BZI,,,M1": 1, ",,M1,,": 1, "M1,,,M2": 1, ",,M2,,": 1, "M2,,,MP": 1, ",,MP,,": 1, "MP,,,MZ": 1, ",,MZ,,": 1, "MZ,,,MZI": 1, ",,MZI,,": 1, "MZI,,,ST": 1, ",,ST,,": 1, "ST,,,SB": 1, ",,SB,,": 1, "SB,,,SM": 1, ",,SM,;": 1, "SM,;,printf": 1, ";,printf,(": 4, "printf,(,\"Unesite bodove za Tarika:\\n\"": 1, "(,\"Unesite bodove za Tarika:\\n\",)": 1, "\"Unesite bodove za Tarika:\\n\",),;": 1, "),;,printf": 3, "printf,(,\"I parcijalni ispit: \"": 3, "(,\"I parcijalni ispit: \",)": 3, "\"I parcijalni ispit: \",),;": 3, "),;,scanf": 15, ";,scanf,(": 15, "scanf,(,\"%lf\"": 15, "(,\"%lf\",,": 15, "\"%lf\",,,&": 15, ",,&,T1": 1, "&,T1,)": 1, "T1,),;": 1, "),;,if": 14, ";,if,(": 31, "if,(,T1": 1, "(,T1,<": 1, "T1,<,0": 1, "<,0,||": 15, "0,||,T1": 1, "||,T1,>": 1, "T1,>,20": 1, ">,20,)": 6, "20,),{": 6, "),{,printf": 28, "{,printf,(": 42, "printf,(,\"Neispravan broj bodova \"": 15, "(,\"Neispravan broj bodova \",)": 15, "\"Neispravan broj bodova \",),;": 15, "),;,}": 29, ";,},else": 26, "},else,{": 15, "else,{,printf": 14, "printf,(,\"II parcijalni ispit: \"": 3, "(,\"II parcijalni ispit: \",)": 3, "\"II parcijalni ispit: \",),;": 3, ",,&,T2": 1, "&,T2,)": 1, "T2,),;": 1, "if,(,T2": 1, "(,T2,<": 1, "T2,<,0": 1, "0,||,T2": 1, "||,T2,>": 1, "T2,>,20": 1, "printf,(,\"Prisustvo: \"": 3, "(,\"Prisustvo: \",)": 3, "\"Prisustvo: \",),;": 3, ",,&,TP": 1, "&,TP,)": 1, "TP,),;": 1, "if,(,TP": 1, "(,TP,<": 1, "TP,<,0": 1, "0,||,TP": 1, "||,TP,>": 1, "TP,>,10": 1, ">,10,)": 6, "10,),{": 6, "printf,(,\"Zadace: \"": 3, "(,\"Zadace: \",)": 3, "\"Zadace: \",),;": 3, ",,&,TZ": 1, "&,TZ,)": 1, "TZ,),;": 1, "if,(,TZ": 1, "(,TZ,<": 1, "TZ,<,0": 1, "0,||,TZ": 1, "||,TZ,>": 1, "TZ,>,10": 1, "printf,(,\"Zavrsni ispit: \"": 3, "(,\"Zavrsni ispit: \",)": 3, "\"Zavrsni ispit: \",),;": 3, ",,&,TZI": 1, "&,TZI,)": 1, "TZI,),;": 1, "if,(,TZI": 1, "(,TZI,<": 1, "TZI,<,0": 1, "0,||,TZI": 1, "||,TZI,>": 1, "TZI,>,40": 1, ">,40,)": 3, "40,),{": 3, "printf,(,\"Unesite bodove za Bojana:\\n\"": 1, "(,\"Unesite bodove za Bojana:\\n\",)": 1, "\"Unesite bodove za Bojana:\\n\",),;": 1, ",,&,B1": 1, "&,B1,)": 1, "B1,),;": 1, ";,},if": 1, "},if,(": 1, "if,(,B1": 1, "(,B1,<": 1, "B1,<,0": 1, "0,||,B1": 1, "||,B1,>": 1, "B1,>,20": 1, ",,&,B2": 1, "&,B2,)": 1, "B2,),;": 1, "if,(,B2": 1, "(,B2,<": 1, "B2,<,0": 1, "0,||,B2": 1, "||,B2,>": 1, "B2,>,20": 1, ",,&,BP": 1, "&,BP,)": 1, "BP,),;": 1, "if,(,BP": 1, "(,BP,<": 1, "BP,<,0": 1, "0,||,BP": 1, "||,BP,>": 1, "BP,>,10": 1, ",,&,BZ": 1, "&,BZ,)": 1, "BZ,),;": 1, "if,(,BZ": 1, "(,BZ,<": 1, "BZ,<,0": 1, "0,||,BZ": 1, "||,BZ,>": 1, "BZ,>,10": 1, ",,&,BZI": 1, "&,BZI,)": 1, "BZI,),;": 1, "if,(,BZI": 1, "(,BZI,<": 1, "BZI,<,0": 1, "0,||,BZI": 1, "||,BZI,>": 1, "BZI,>,40": 1, "printf,(,\"Unesite bodove za Mirzu:\\n\"": 1, "(,\"Unesite bodove za Mirzu:\\n\",)": 1, "\"Unesite bodove za Mirzu:\\n\",),;": 1, ",,&,M1": 1, "&,M1,)": 1, "M1,),;": 1, "if,(,M1": 1, "(,M1,<": 1, "M1,<,0": 1, "0,||,M1": 1, "||,M1,>": 1, "M1,>,20": 1, ",,&,M2": 1, "&,M2,)": 1, "M2,),;": 1, "if,(,M2": 1, "(,M2,<": 1, "M2,<,0": 1, "0,||,M2": 1, "||,M2,>": 1, "M2,>,20": 1, ",,&,MP": 1, "&,MP,)": 1, "MP,),;": 1, "if,(,MP": 1, "(,MP,<": 1, "MP,<,0": 1, "0,||,MP": 1, "||,MP,>": 1, "MP,>,10": 1, ",,&,MZ": 1, "&,MZ,)": 1, "MZ,),;": 1, "if,(,MZ": 1, "(,MZ,<": 1, "MZ,<,0": 1, "0,||,MZ": 1, "||,MZ,>": 1, "MZ,>,10": 1, ",,&,MZI": 1, "&,MZI,)": 1, "MZI,),;": 1, "if,(,MZI": 1, "(,MZI,<": 1, "MZI,<,0": 1, "0,||,MZI": 1, "||,MZI,>": 1, "MZI,>,40": 1, "else,{,ST": 1, "{,ST,=": 1, "ST,=,T1": 1, "=,T1,+": 1, "T1,+,T2": 1, "+,T2,+": 1, "T2,+,TP": 1, "+,TP,+": 1, "TP,+,TZ": 1, "+,TZ,+": 1, "TZ,+,TZI": 1, "+,TZI,;": 1, "TZI,;,SB": 1, ";,SB,=": 1, "SB,=,B1": 1, "=,B1,+": 1, "B1,+,B2": 1, "+,B2,+": 1, "B2,+,BP": 1, "+,BP,+": 1, "BP,+,BZ": 1, "+,BZ,+": 1, "BZ,+,BZI": 1, "+,BZI,;": 1, "BZI,;,SM": 1, ";,SM,=": 1, "SM,=,M1": 1, "=,M1,+": 1, "M1,+,M2": 1, "+,M2,+": 1, "M2,+,MP": 1, "+,MP,+": 1, "MP,+,MZ": 1, "+,MZ,+": 1, "MZ,+,MZI": 1, "+,MZI,;": 1, "MZI,;,if": 1, "if,(,ST": 14, "(,ST,>=": 10, "ST,>=,55": 6, ">=,55,&&": 10, "55,&&,SB": 9, "&&,SB,>=": 5, "SB,>=,55": 6, "55,&&,SM": 9, "&&,SM,>=": 5, "SM,>=,55": 6, ">=,55,)": 8, "55,),{": 9, "printf,(,\"Sva tri studenta su polozila.\\n\"": 1, "(,\"Sva tri studenta su polozila.\\n\",)": 1, "\"Sva tri studenta su polozila.\\n\",),;": 1, "},else,if": 11, "else,if,(": 11, "&&,SM,<": 4, "SM,<,55": 4, "<,55,)": 4, "printf,(,\"Dva studenta su polozila.\\n\"": 3, "(,\"Dva studenta su polozila.\\n\",)": 3, "\"Dva studenta su polozila.\\n\",),;": 3, "&&,SB,<": 4, "SB,<,55": 4, "<,55,&&": 8, "(,ST,<": 4, "ST,<,55": 4, "printf,(,\"Jedan student je polozio.\\n\"": 3, "(,\"Jedan student je polozio.\\n\",)": 3, "\"Jedan student je polozio.\\n\",),;": 3, "printf,(,\"Nijedan student nije polozio.\\n\"": 1, "(,\"Nijedan student nije polozio.\\n\",)": 1, "\"Nijedan student nije polozio.\\n\",),;": 1, ";,},int": 1, "},int,OT": 1, "int,OT,,": 1, "OT,,,OB": 1, ",,OB,,": 1, "OB,,,OM": 1, ",,OM,;": 1, "OM,;,if": 1, "55,),OT": 1, "),OT,=": 5, "OT,=,6": 1, "=,6,;": 3, "6,;,if": 3, "ST,>=,65": 1, ">=,65,)": 3, "65,),OT": 1, "OT,=,7": 1, "=,7,;": 3, "7,;,if": 3, "ST,>=,75": 1, ">=,75,)": 3, "75,),OT": 1, "OT,=,8": 1, "=,8,;": 3, "8,;,if": 3, "ST,>=,85": 1, ">=,85,)": 3, "85,),OT": 1, "OT,=,9": 1, "=,9,;": 3, "9,;,if": 3, "ST,>=,92": 1, ">=,92,)": 3, "92,),OT": 1, "OT,=,10": 1, "=,10,;": 3, "10,;,if": 3, "if,(,SB": 5, "(,SB,>=": 5, "55,),OB": 1, "),OB,=": 5, "OB,=,6": 1, "SB,>=,65": 1, "65,),OB": 1, "OB,=,7": 1, "SB,>=,75": 1, "75,),OB": 1, "OB,=,8": 1, "SB,>=,85": 1, "85,),OB": 1, "OB,=,9": 1, "SB,>=,92": 1, "92,),OB": 1, "OB,=,10": 1, "if,(,SM": 5, "(,SM,>=": 5, "55,),OM": 1, "),OM,=": 5, "OM,=,6": 1, "SM,>=,65": 1, "65,),OM": 1, "OM,=,7": 1, "SM,>=,75": 1, "75,),OM": 1, "OM,=,8": 1, "SM,>=,85": 1, "85,),OM": 1, "OM,=,9": 1, "SM,>=,92": 1, "92,),OM": 1, "OM,=,10": 1, "),{,if": 1, "{,if,(": 1, "if,(,OT": 4, "(,OT,==": 3, "OT,==,OB": 2, "==,OB,&&": 2, "OB,&&,OT": 2, "&&,OT,==": 1, "OT,==,OM": 2, "==,OM,)": 1, "OM,),{": 4, "printf,(,\"Sva tri studenta imaju istu ocjenu. \"": 1, "(,\"Sva tri studenta imaju istu ocjenu. \",)": 1, "\"Sva tri studenta imaju istu ocjenu. \",),;": 1, "OB,&&,OB": 1, "&&,OB,!=": 3, "OB,!=,OM": 3, "!=,OM,)": 3, "printf,(,\"Dva od tri studenta imaju istu ocjenu. \"": 3, "(,\"Dva od tri studenta imaju istu ocjenu. \",)": 3, "\"Dva od tri studenta imaju istu ocjenu. \",),;": 3, "==,OM,&&": 2, "OM,&&,OB": 2, "if,(,OB": 1, "(,OB,==": 1, "OB,==,OM": 1, "OM,&&,OM": 1, "&&,OM,!=": 1, "OM,!=,OT": 1, "!=,OT,)": 1, "OT,),{": 1, "(,OT,!=": 1, "OT,!=,OB": 1, "!=,OB,&&": 1, "&&,OT,!=": 1, "OT,!=,OM": 1, "!=,OM,&&": 1, "printf,(,\"Svaki student ima razlicitu ocjenu. \"": 1, "(,\"Svaki student ima razlicitu ocjenu. \",)": 1, "\"Svaki student ima razlicitu ocjenu. \",),;": 1, ";,},}": 2, "},},return": 1, "},return,0": 1, "return,0,;": 1, "0,;,}": 1, "},},}": 13}