{"#include <stdio.h>,int,main": 1, "int,main,(": 1, "main,(,)": 1, "(,),{": 1, "),{,double": 1, "{,double,ppt": 1, "double,ppt,=": 1, "ppt,=,0": 1, "=,0,,": 15, "0,,,dpt": 1, ",,dpt,=": 1, "dpt,=,0": 1, "0,,,prist": 1, ",,prist,=": 1, "prist,=,0": 1, "0,,,zadt": 1, ",,zadt,=": 1, "zadt,=,0": 1, "0,,,zavt": 1, ",,zavt,=": 1, "zavt,=,0": 1, "0,,,ukt": 1, ",,ukt,=": 1, "ukt,=,0": 1, "=,0,;": 9, "0,;,int": 3, ";,int,ot": 1, "int,ot,=": 1, "ot,=,0": 2, "0,;,double": 2, ";,double,ppb": 1, "double,ppb,=": 1, "ppb,=,0": 1, "0,,,dpb": 1, ",,dpb,=": 1, "dpb,=,0": 1, "0,,,prisb": 1, ",,prisb,=": 1, "prisb,=,0": 1, "0,,,zadb": 1, ",,zadb,=": 1, "zadb,=,0": 1, "0,,,zavb": 1, ",,zavb,=": 1, "zavb,=,0": 1, "0,,,ukb": 1, ",,ukb,=": 1, "ukb,=,0": 1, ";,int,ob": 1, "int,ob,=": 1, "ob,=,0": 2, ";,double,ppm": 1, "double,ppm,=": 1, "ppm,=,0": 1, "0,,,dpm": 1, ",,dpm,=": 1, "dpm,=,0": 1, "0,,,prism": 1, ",,prism,=": 1, "prism,=,0": 1, "0,,,zadm": 1, ",,zadm,=": 1, "zadm,=,0": 1, "0,,,zavm": 1, ",,zavm,=": 1, "zavm,=,0": 1, "0,,,ukm": 1, ",,ukm,=": 1, "ukm,=,0": 1, ";,int,om": 1, "int,om,=": 1, "om,=,0": 2, "0,;,printf": 1, ";,printf,(": 4, "printf,(,\"Unesite bodove za Tarika: \\n\"": 1, "(,\"Unesite bodove za Tarika: \\n\",)": 1, "\"Unesite bodove za Tarika: \\n\",),;": 1, "),;,printf": 3, "printf,(,\"I parcijalni ispit: \"": 3, "(,\"I parcijalni ispit: \",)": 3, "\"I parcijalni ispit: \",),;": 3, "),;,scanf": 15, ";,scanf,(": 15, "scanf,(,\"%lf\"": 15, "(,\"%lf\",,": 15, "\"%lf\",,,&": 15, ",,&,ppt": 1, "&,ppt,)": 1, "ppt,),;": 1, "),;,if": 16, ";,if,(": 19, "if,(,ppt": 1, "(,ppt,<": 1, "ppt,<,0": 1, "<,0,||": 15, "0,||,ppt": 1, "||,ppt,>": 1, "ppt,>,20": 1, ">,20,)": 6, "20,),{": 6, "),{,printf": 22, "{,printf,(": 22, "printf,(,\"Neispravan broj bodova\"": 15, "(,\"Neispravan broj bodova\",)": 15, "\"Neispravan broj bodova\",),;": 15, "),;,return": 21, ";,return,0": 21, "return,0,;": 22, "0,;,}": 25, ";,},printf": 12, "},printf,(": 14, "printf,(,\"II parcijalni ispit: \"": 3, "(,\"II parcijalni ispit: \",)": 3, "\"II parcijalni ispit: \",),;": 3, ",,&,dpt": 1, "&,dpt,)": 1, "dpt,),;": 1, "if,(,dpt": 1, "(,dpt,<": 1, "dpt,<,0": 1, "0,||,dpt": 1, "||,dpt,>": 1, "dpt,>,20": 1, "printf,(,\"Prisustvo: \"": 3, "(,\"Prisustvo: \",)": 3, "\"Prisustvo: \",),;": 3, ",,&,prist": 1, "&,prist,)": 1, "prist,),;": 1, "if,(,prist": 1, "(,prist,<": 1, "prist,<,0": 1, "0,||,prist": 1, "||,prist,>": 1, "prist,>,10": 1, ">,10,)": 6, "10,),{": 6, "printf,(,\"Zadace: \"": 3, "(,\"Zadace: \",)": 3, "\"Zadace: \",),;": 3, ",,&,zadt": 1, "&,zadt,)": 1, "zadt,),;": 1, "if,(,zadt": 1, "(,zadt,<": 1, "zadt,<,0": 1, "0,||,zadt": 1, "||,zadt,>": 1, "zadt,>,10": 1, "printf,(,\"Zavrsni ispit: \"": 3, "(,\"Zavrsni ispit: \",)": 3, "\"Zavrsni ispit: \",),;": 3, ",,&,zavt": 1, "&,zavt,)": 1, "zavt,),;": 1, "if,(,zavt": 1, "(,zavt,<": 1, "zavt,<,0": 1, "0,||,zavt": 1, "||,zavt,>": 1, "zavt,>,40": 1, ">,40,)": 3, "40,),{": 3, ";,},ukt": 1, "},ukt,=": 1, "ukt,=,ppt": 1, "=,ppt,+": 1, "ppt,+,dpt": 1, "+,dpt,+": 1, "dpt,+,zadt": 1, "+,zadt,+": 1, "zadt,+,prist": 1, "+,prist,+": 1, "prist,+,zavt": 1, "+,zavt,;": 1, "zavt,;,if": 1, "if,(,ukt": 6, "(,ukt,<": 1, "ukt,<,55": 1, "<,55,)": 3, "55,),{": 3, "),{,ot": 6, "{,ot,=": 6, ";,},else": 3, "},else,{": 3, "else,{,if": 3, "{,if,(": 3, "(,ukt,>=": 5, "ukt,>=,55": 1, ">=,55,&&": 3, "55,&&,ukt": 1, "&&,ukt,<": 5, "ukt,<,65": 1, "<,65,)": 3, "65,),{": 3, "ot,=,6": 1, "=,6,;": 3, "6,;,}": 3, ";,},if": 17, "},if,(": 18, "ukt,>=,65": 1, ">=,65,&&": 3, "65,&&,ukt": 1, "ukt,<,75": 1, "<,75,)": 3, "75,),{": 3, "ot,=,7": 1, "=,7,;": 3, "7,;,}": 3, "ukt,>=,75": 1, ">=,75,&&": 3, "75,&&,ukt": 1, "ukt,<,85": 1, "<,85,)": 3, "85,),{": 3, "ot,=,8": 1, "=,8,;": 3, "8,;,}": 3, "ukt,>=,85": 1, ">=,85,&&": 3, "85,&&,ukt": 1, "ukt,<,92": 1, "<,92,)": 3, "92,),{": 3, "ot,=,9": 1, "=,9,;": 3, "9,;,}": 3, "ukt,>=,92": 1, ">=,92,&&": 3, "92,&&,ukt": 1, "ukt,<,100": 1, "<,100,)": 3, "100,),{": 3, "ot,=,10": 1, "=,10,;": 3, "10,;,}": 3, ";,},}": 4, "},},printf": 2, "printf,(,\"Unesite bodove za Bojana: \\n\"": 1, "(,\"Unesite bodove za Bojana: \\n\",)": 1, "\"Unesite bodove za Bojana: \\n\",),;": 1, ",,&,ppb": 1, "&,ppb,)": 1, "ppb,),;": 1, "if,(,ppb": 1, "(,ppb,<": 1, "ppb,<,0": 1, "0,||,ppb": 1, "||,ppb,>": 1, "ppb,>,20": 1, ",,&,dpb": 1, "&,dpb,)": 1, "dpb,),;": 1, "if,(,dpb": 1, "(,dpb,<": 1, "dpb,<,0": 1, "0,||,dpb": 1, "||,dpb,>": 1, "dpb,>,20": 1, ",,&,prisb": 1, "&,prisb,)": 1, "prisb,),;": 1, "if,(,prisb": 1, "(,prisb,<": 1, "prisb,<,0": 1, "0,||,prisb": 1, "||,prisb,>": 1, "prisb,>,10": 1, ",,&,zadb": 1, "&,zadb,)": 1, "zadb,),;": 1, "if,(,zadb": 1, "(,zadb,<": 1, "zadb,<,0": 1, "0,||,zadb": 1, "||,zadb,>": 1, "zadb,>,10": 1, ",,&,zavb": 1, "&,zavb,)": 1, "zavb,),;": 1, "if,(,zavb": 1, "(,zavb,<": 1, "zavb,<,0": 1, "0,||,zavb": 1, "||,zavb,>": 1, "zavb,>,40": 1, ";,},ukb": 1, "},ukb,=": 1, "ukb,=,ppb": 1, "=,ppb,+": 1, "ppb,+,dpb": 1, "+,dpb,+": 1, "dpb,+,zadb": 1, "+,zadb,+": 1, "zadb,+,prisb": 1, "+,prisb,+": 1, "prisb,+,zavb": 1, "+,zavb,;": 1, "zavb,;,if": 1, "if,(,ukb": 6, "(,ukb,<": 1, "ukb,<,55": 1, "),{,ob": 6, "{,ob,=": 6, "(,ukb,>=": 5, "ukb,>=,55": 1, "55,&&,ukb": 1, "&&,ukb,<": 5, "ukb,<,65": 1, "ob,=,6": 1, "ukb,>=,65": 1, "65,&&,ukb": 1, "ukb,<,75": 1, "ob,=,7": 1, "ukb,>=,75": 1, "75,&&,ukb": 1, "ukb,<,85": 1, "ob,=,8": 1, "ukb,>=,85": 1, "85,&&,ukb": 1, "ukb,<,92": 1, "ob,=,9": 1, "ukb,>=,92": 1, "92,&&,ukb": 1, "ukb,<,100": 1, "ob,=,10": 1, "printf,(,\"Unesite bodove za Mirzu: \\n\"": 1, "(,\"Unesite bodove za Mirzu: \\n\",)": 1, "\"Unesite bodove za Mirzu: \\n\",),;": 1, ",,&,ppm": 1, "&,ppm,)": 1, "ppm,),;": 1, "if,(,ppm": 1, "(,ppm,<": 1, "ppm,<,0": 1, "0,||,ppm": 1, "||,ppm,>": 1, "ppm,>,20": 1, ",,&,dpm": 1, "&,dpm,)": 1, "dpm,),;": 1, "if,(,dpm": 1, "(,dpm,<": 1, "dpm,<,0": 1, "0,||,dpm": 1, "||,dpm,>": 1, "dpm,>,20": 1, ",,&,prism": 1, "&,prism,)": 1, "prism,),;": 1, "if,(,prism": 1, "(,prism,<": 1, "prism,<,0": 1, "0,||,prism": 1, "||,prism,>": 1, "prism,>,10": 1, ",,&,zadm": 1, "&,zadm,)": 1, "zadm,),;": 1, "if,(,zadm": 1, "(,zadm,<": 1, "zadm,<,0": 1, "0,||,zadm": 1, "||,zadm,>": 1, "zadm,>,10": 1, ",,&,zavm": 1, "&,zavm,)": 1, "zavm,),;": 1, "if,(,zavm": 1, "(,zavm,<": 1, "zavm,<,0": 1, "0,||,zavm": 1, "||,zavm,>": 1, "zavm,>,40": 1, ";,},ukm": 1, "},ukm,=": 1, "ukm,=,ppm": 1, "=,ppm,+": 1, "ppm,+,dpm": 1, "+,dpm,+": 1, "dpm,+,zadm": 1, "+,zadm,+": 1, "zadm,+,prism": 1, "+,prism,+": 1, "prism,+,zavm": 1, "+,zavm,;": 1, "zavm,;,if": 1, "if,(,ukm": 6, "(,ukm,<": 1, "ukm,<,55": 1, "),{,om": 6, "{,om,=": 6, "(,ukm,>=": 5, "ukm,>=,55": 1, "55,&&,ukm": 1, "&&,ukm,<": 5, "ukm,<,65": 1, "om,=,6": 1, "ukm,>=,65": 1, "65,&&,ukm": 1, "ukm,<,75": 1, "om,=,7": 1, "ukm,>=,75": 1, "75,&&,ukm": 1, "ukm,<,85": 1, "om,=,8": 1, "ukm,>=,85": 1, "85,&&,ukm": 1, "ukm,<,92": 1, "om,=,9": 1, "ukm,>=,92": 1, "92,&&,ukm": 1, "ukm,<,100": 1, "om,=,10": 1, "},},if": 1, "if,(,om": 1, "(,om,==": 1, "om,==,0": 4, "==,0,&&": 8, "0,&&,ob": 8, "&&,ob,==": 4, "ob,==,0": 4, "0,&&,ot": 1, "&&,ot,==": 2, "ot,==,0": 4, "==,0,)": 4, "0,),{": 2, "printf,(,\"Nijedan student nije polozio.\"": 1, "(,\"Nijedan student nije polozio.\",)": 1, "\"Nijedan student nije polozio.\",),;": 1, "if,(,(": 3, "(,(,ot": 3, "(,ot,!=": 5, "ot,!=,0": 4, "!=,0,&&": 8, "0,&&,om": 7, "&&,om,==": 3, "0,),||": 4, "),||,(": 6, "||,(,ot": 5, "(,ot,==": 6, "&&,ob,!=": 7, "ob,!=,0": 4, "&&,om,!=": 4, "om,!=,0": 4, "!=,0,)": 4, "0,),)": 2, "),),{": 3, "printf,(,\"Jedan student je polozio.\"": 1, "(,\"Jedan student je polozio.\",)": 1, "\"Jedan student je polozio.\",),;": 1, "printf,(,\"Dva studenta su polozila.\"": 1, "(,\"Dva studenta su polozila.\",)": 1, "\"Dva studenta su polozila.\",),;": 1, "if,(,ot": 3, "printf,(,\"Sva tri studenta su polozila.\\n\"": 1, "(,\"Sva tri studenta su polozila.\\n\",)": 1, "\"Sva tri studenta su polozila.\\n\",),;": 1, "ot,==,ob": 2, "==,ob,&&": 2, "ob,&&,ot": 2, "ot,==,om": 2, "==,om,)": 1, "om,),{": 2, "printf,(,\"Sva tri studenta imaju istu ocjenu.\"": 1, "(,\"Sva tri studenta imaju istu ocjenu.\",)": 1, "\"Sva tri studenta imaju istu ocjenu.\",),;": 1, "ob,&&,ob": 1, "ob,!=,om": 2, "!=,om,)": 2, "om,),||": 1, "||,(,ob": 1, "(,ob,==": 1, "ob,==,om": 1, "==,om,&&": 2, "om,&&,ob": 2, "ob,!=,ot": 1, "!=,ot,)": 1, "ot,),||": 1, "om,&&,ot": 1, "&&,ot,!=": 2, "ot,!=,ob": 2, "!=,ob,)": 1, "ob,),)": 1, "printf,(,\"Dva od tri studenta imaju istu ocjenu.\"": 1, "(,\"Dva od tri studenta imaju istu ocjenu.\",)": 1, "\"Dva od tri studenta imaju istu ocjenu.\",),;": 1, "!=,ob,&&": 1, "ot,!=,om": 1, "!=,om,&&": 1, "printf,(,\"Svaki student ima razlicitu ocjenu.\"": 1, "(,\"Svaki student ima razlicitu ocjenu.\",)": 1, "\"Svaki student ima razlicitu ocjenu.\",),;": 1, "},},return": 1, "},return,0": 1}