{"#include <stdio.h>,#include <stdlib.h>,#include <math.h>": 1, "#include <stdlib.h>,#include <math.h>,int": 1, "#include <math.h>,int,main": 1, "int,main,(": 1, "main,(,)": 1, "(,),{": 1, "),{,float": 1, "{,float,p": 1, "float,p,,": 1, "p,,,d": 1, ",,d,,": 1, "d,,,r": 1, ",,r,,": 1, "r,,,z": 1, ",,z,,": 1, "z,,,i": 1, ",,i,,": 1, "i,,,p1": 1, ",,p1,,": 1, "p1,,,d1": 1, ",,d1,,": 1, "d1,,,r1": 1, ",,r1,,": 1, "r1,,,z1": 1, ",,z1,,": 1, "z1,,,i1": 1, ",,i1,,": 1, "i1,,,p2": 1, ",,p2,,": 1, "p2,,,d2": 1, ",,d2,,": 1, "d2,,,r2": 1, ",,r2,,": 1, "r2,,,z2": 1, ",,z2,,": 1, "z2,,,i2": 1, ",,i2,,": 1, "i2,,,bod": 1, ",,bod,,": 1, "bod,,,bod1": 1, ",,bod1,,": 1, "bod1,,,bod2": 1, ",,bod2,;": 1, "bod2,;,printf": 1, ";,printf,(": 4, "printf,(,\"Unesite bodove za Tarika:\\n\"": 1, "(,\"Unesite bodove za Tarika:\\n\",)": 1, "\"Unesite bodove za Tarika:\\n\",),;": 1, "),;,printf": 3, "printf,(,\"I parcijalni ispit: \"": 3, "(,\"I parcijalni ispit: \",)": 3, "\"I parcijalni ispit: \",),;": 3, "),;,scanf": 15, ";,scanf,(": 15, "scanf,(,\"%f\"": 15, "(,\"%f\",,": 15, "\"%f\",,,&": 15, ",,&,p": 1, "&,p,)": 1, "p,),;": 1, "),;,if": 16, ";,if,(": 17, "if,(,p": 1, "(,p,>": 1, "p,>,20": 1, ">,20,||": 6, "20,||,p": 1, "||,p,<": 1, "p,<,0": 1, "<,0,)": 15, "0,),{": 15, "),{,printf": 28, "{,printf,(": 28, "printf,(,\"Neispravan broj bodova\"": 15, "(,\"Neispravan broj bodova\",)": 15, "\"Neispravan broj bodova\",),;": 15, "),;,return": 14, ";,return,0": 14, "return,0,;": 15, "0,;,}": 15, ";,},printf": 14, "},printf,(": 14, "printf,(,\"II parcijalni ispit: \"": 3, "(,\"II parcijalni ispit: \",)": 3, "\"II parcijalni ispit: \",),;": 3, ",,&,d": 1, "&,d,)": 1, "d,),;": 1, "if,(,d": 1, "(,d,>": 1, "d,>,20": 1, "20,||,d": 1, "||,d,<": 1, "d,<,0": 1, "printf,(,\"Prisustvo: \"": 3, "(,\"Prisustvo: \",)": 3, "\"Prisustvo: \",),;": 3, ",,&,r": 1, "&,r,)": 1, "r,),;": 1, "if,(,r": 1, "(,r,>": 1, "r,>,10": 1, ">,10,||": 6, "10,||,r": 1, "||,r,<": 1, "r,<,0": 1, "printf,(,\"Zadace: \"": 3, "(,\"Zadace: \",)": 3, "\"Zadace: \",),;": 3, ",,&,z": 1, "&,z,)": 1, "z,),;": 1, "if,(,z": 1, "(,z,>": 1, "z,>,10": 1, "10,||,z": 1, "||,z,<": 1, "z,<,0": 1, "),;,}": 14, "printf,(,\"Zavrsni ispit: \"": 3, "(,\"Zavrsni ispit: \",)": 3, "\"Zavrsni ispit: \",),;": 3, ",,&,i": 1, "&,i,)": 1, "i,),;": 1, "if,(,i": 1, "(,i,>": 1, "i,>,40": 1, ">,40,||": 3, "40,||,i": 1, "||,i,<": 1, "i,<,0": 1, "printf,(,\"Unesite bodove za Bojana:\\n\"": 1, "(,\"Unesite bodove za Bojana:\\n\",)": 1, "\"Unesite bodove za Bojana:\\n\",),;": 1, ",,&,p1": 1, "&,p1,)": 1, "p1,),;": 1, "if,(,p1": 1, "(,p1,>": 1, "p1,>,20": 1, "20,||,p1": 1, "||,p1,<": 1, "p1,<,0": 1, ",,&,d1": 1, "&,d1,)": 1, "d1,),;": 1, "if,(,d1": 1, "(,d1,>": 1, "d1,>,20": 1, "20,||,d1": 1, "||,d1,<": 1, "d1,<,0": 1, ",,&,r1": 1, "&,r1,)": 1, "r1,),;": 1, "if,(,r1": 1, "(,r1,>": 1, "r1,>,10": 1, "10,||,r1": 1, "||,r1,<": 1, "r1,<,0": 1, ",,&,z1": 1, "&,z1,)": 1, "z1,),;": 1, "if,(,z1": 1, "(,z1,>": 1, "z1,>,10": 1, "10,||,z1": 1, "||,z1,<": 1, "z1,<,0": 1, ",,&,i1": 1, "&,i1,)": 1, "i1,),;": 1, "if,(,i1": 1, "(,i1,>": 1, "i1,>,40": 1, "40,||,i1": 1, "||,i1,<": 1, "i1,<,0": 1, "printf,(,\"Unesite bodove za Mirzu:\\n\"": 1, "(,\"Unesite bodove za Mirzu:\\n\",)": 1, "\"Unesite bodove za Mirzu:\\n\",),;": 1, ",,&,p2": 1, "&,p2,)": 1, "p2,),;": 1, "if,(,p2": 1, "(,p2,>": 1, "p2,>,20": 1, "20,||,p2": 1, "||,p2,<": 1, "p2,<,0": 1, ",,&,d2": 1, "&,d2,)": 1, "d2,),;": 1, "if,(,d2": 1, "(,d2,>": 1, "d2,>,20": 1, "20,||,d2": 1, "||,d2,<": 1, "d2,<,0": 1, ",,&,r2": 1, "&,r2,)": 1, "r2,),;": 1, "if,(,r2": 1, "(,r2,>": 1, "r2,>,10": 1, "10,||,r2": 1, "||,r2,<": 1, "r2,<,0": 1, ",,&,z2": 1, "&,z2,)": 1, "z2,),;": 1, "if,(,z2": 1, "(,z2,>": 1, "z2,>,10": 1, "10,||,z2": 1, "||,z2,<": 1, "z2,<,0": 1, ",,&,i2": 1, "&,i2,)": 1, "i2,),;": 1, "if,(,i2": 1, "(,i2,>": 1, "i2,>,40": 1, "40,||,i2": 1, "||,i2,<": 1, "i2,<,0": 1, ";,},bod": 1, "},bod,=": 1, "bod,=,p": 1, "=,p,+": 1, "p,+,d": 1, "+,d,+": 1, "d,+,r": 1, "+,r,+": 1, "r,+,z": 1, "+,z,+": 1, "z,+,i": 1, "+,i,;": 1, "i,;,bod1": 1, ";,bod1,=": 1, "bod1,=,p1": 1, "=,p1,+": 1, "p1,+,d2": 1, "+,d2,+": 2, "d2,+,r1": 1, "+,r1,+": 1, "r1,+,z1": 1, "+,z1,+": 1, "z1,+,i1": 1, "+,i1,;": 1, "i1,;,bod2": 1, ";,bod2,=": 1, "bod2,=,p2": 1, "=,p2,+": 1, "p2,+,d2": 1, "d2,+,r2": 1, "+,r2,+": 1, "r2,+,z2": 1, "+,z2,+": 1, "z2,+,i2": 1, "+,i2,;": 1, "i2,;,if": 1, "if,(,bod": 2, "(,bod,<": 4, "bod,<,55": 4, "<,55,&&": 8, "55,&&,bod1": 8, "&&,bod1,<": 4, "bod1,<,55": 4, "55,&&,bod2": 12, "&&,bod2,<": 18, "bod2,<,55": 4, "<,55,)": 4, "55,),{": 1, "printf,(,\"Nijedan student nije polozio.\"": 1, "(,\"Nijedan student nije polozio.\",)": 1, "\"Nijedan student nije polozio.\",),;": 1, ";,},if": 12, "},if,(": 12, "(,bod,>=": 20, "bod,>=,55": 8, ">=,55,&&": 20, "&&,bod1,>=": 4, "bod1,>=,55": 8, "&&,bod2,>=": 4, "bod2,>=,55": 8, ">=,55,)": 4, "55,),printf": 1, "),printf,(": 1, "printf,(,\"Sva tri studenta su polozila.\"": 1, "(,\"Sva tri studenta su polozila.\",)": 1, "\"Sva tri studenta su polozila.\",),;": 1, "if,(,(": 12, "(,(,bod": 12, "55,),||": 4, "),||,(": 14, "||,(,bod": 14, "55,),)": 2, "),),{": 12, "printf,(,\"Jedan student je polozio.\"": 1, "(,\"Jedan student je polozio.\",)": 1, "\"Jedan student je polozio.\",),;": 1, "printf,(,\"Dva studenta su polozila.\"": 1, "(,\"Dva studenta su polozila.\",)": 1, "\"Dva studenta su polozila.\",),;": 1, "55,&&,bod": 8, "&&,bod,<": 28, "bod,<,65": 6, "<,65,)": 9, "65,),&&": 8, "),&&,(": 40, "&&,(,bod1": 20, "(,bod1,>=": 16, "&&,(,bod2": 20, "(,bod2,>=": 16, "bod2,<,65": 3, "65,),)": 2, "printf,(,\"\\nSva tri studenta imaju istu ocjenu.\"": 5, "(,\"\\nSva tri studenta imaju istu ocjenu.\",)": 5, "\"\\nSva tri studenta imaju istu ocjenu.\",),;": 5, "&&,bod2,>": 4, "bod2,>,65": 1, ">,65,)": 3, "65,),||": 2, "&&,bod,>": 10, "bod,>,65": 2, "printf,(,\"\\nDva od tri studenta imaju istu ocjenu.\"": 5, "(,\"\\nDva od tri studenta imaju istu ocjenu.\",)": 5, "\"\\nDva od tri studenta imaju istu ocjenu.\",),;": 5, "bod,>=,65": 3, ">=,65,&&": 9, "65,&&,bod": 8, "bod,<,75": 6, "<,75,)": 9, "75,),&&": 8, "bod1,>=,65": 3, "bod2,>=,65": 3, "65,&&,bod2": 4, "bod2,<,75": 3, "75,),)": 2, "(,bod2,<=": 4, "bod2,<=,65": 1, "<=,65,&&": 3, "bod2,>,75": 1, ">,75,)": 3, "75,),||": 2, "bod,>,75": 2, "(,bod1,<=": 4, "bod1,<=,65": 1, "(,bod,<=": 4, "bod,<=,65": 1, "bod,>=,75": 3, ">=,75,&&": 9, "75,&&,bod": 8, "bod,<,85": 6, "<,85,)": 9, "85,),&&": 8, "bod1,>=,75": 3, "bod2,>=,75": 3, "75,&&,bod2": 4, "bod2,<,85": 3, "85,),)": 2, "bod2,<=,75": 1, "<=,75,&&": 3, "bod2,>,85": 1, ">,85,)": 3, "85,),||": 2, "bod,>,85": 2, "bod1,<=,75": 1, "bod,<=,75": 1, "bod,>=,85": 3, ">=,85,&&": 9, "85,&&,bod": 8, "bod,<,92": 6, "<,92,)": 9, "92,),&&": 10, "bod1,>=,85": 3, "bod2,>=,85": 3, "85,&&,bod2": 4, "bod2,<,92": 3, "92,),)": 2, "bod2,<=,85": 1, "<=,85,&&": 3, "bod2,>,92": 1, ">,92,)": 3, "92,),||": 3, "bod,>,92": 2, "bod1,<=,85": 1, "bod,<=,85": 1, "bod,>=,92": 3, ">=,92,&&": 8, "92,&&,bod": 6, "bod,<,100": 4, "<,100,)": 7, "100,),&&": 6, "bod1,>=,92": 3, "bod2,>=,92": 3, "92,&&,bod2": 2, "bod2,<,100": 3, "100,),)": 2, "bod2,<=,92": 1, "<=,92,)": 3, "bod,>,100": 2, ">,100,)": 2, "bod1,<=,92": 1, "100,),||": 1, "bod,<=,92": 1, ">=,92,||": 1, "92,||,bod2": 1, "||,bod2,<": 1, ";,},return": 1, "},return,0": 1}