{"#include <stdio.h>,int": 1, "int,main": 1, "main,(": 1, "(,)": 1, "),{": 70, "{,float": 1, "float,P11": 1, "P11,,": 1, ",,P21": 1, "P21,,": 1, ",,p1": 1, "p1,,": 1, ",,DZ1": 1, "DZ1,,": 1, ",,Z1": 1, "Z1,,": 1, ",,P12": 1, "P12,,": 1, ",,P22": 1, "P22,,": 1, ",,p2": 1, "p2,,": 1, ",,DZ2": 1, "DZ2,,": 1, ",,Z2": 1, "Z2,,": 1, ",,P13": 1, "P13,,": 1, ",,P23": 1, "P23,,": 1, ",,p3": 1, "p3,,": 1, ",,DZ3": 1, "DZ3,,": 1, ",,Z3": 1, "Z3,,": 1, ",,O1": 1, "O1,=": 2, "=,0": 3, "0,,": 2, ",,O2": 1, "O2,=": 2, ",,O3": 1, "O3,=": 2, "0,;": 17, ";,printf": 2, "printf,(": 87, "(,\"Unesite bodove za Tarika:\\n\"": 1, "\"Unesite bodove za Tarika:\\n\",)": 1, "),;": 102, "(,\"I parcijalni ispit: \"": 3, "\"I parcijalni ispit: \",)": 3, ";,scanf": 3, "scanf,(": 15, "(,\"%f\"": 15, "\"%f\",,": 15, ",,&": 15, "&,P11": 1, "P11,)": 1, ";,if": 16, "if,(": 69, "(,P11": 1, "P11,<": 1, "<,0.0": 15, "0.0,||": 15, "||,P11": 1, "P11,>": 1, ">,20.0": 6, "20.0,)": 6, "{,printf": 83, "(,\"Neispravan broj bodova\"": 15, "\"Neispravan broj bodova\",)": 15, ";,return": 15, "return,0": 16, ";,}": 84, "},else": 68, "else,{": 15, "(,\"II parcijalni ispit: \"": 3, "\"II parcijalni ispit: \",)": 3, "},scanf": 12, "&,P21": 1, "P21,)": 1, "(,P21": 1, "P21,<": 1, "||,P21": 1, "P21,>": 1, "(,\"Prisustvo: \"": 3, "\"Prisustvo: \",)": 3, "&,p1": 1, "p1,)": 1, "(,p1": 1, "p1,<": 1, "||,p1": 1, "p1,>": 1, ">,10.0": 6, "10.0,)": 6, "(,\"Zadace: \"": 3, "\"Zadace: \",)": 3, "&,DZ1": 1, "DZ1,)": 1, "(,DZ1": 1, "DZ1,<": 1, "||,DZ1": 1, "DZ1,>": 1, "(,\"Zavrsni ispit: \"": 3, "\"Zavrsni ispit: \",)": 3, "&,Z1": 1, "Z1,)": 1, "(,Z1": 1, "Z1,<": 1, "||,Z1": 1, "Z1,>": 1, ">,40.0": 3, "40.0,)": 3, "(,\"Unesite bodove za Bojana:\\n\"": 1, "\"Unesite bodove za Bojana:\\n\",)": 1, "},printf": 2, "&,P12": 1, "P12,)": 1, "(,P12": 1, "P12,<": 1, "||,P12": 1, "P12,>": 1, "&,P22": 1, "P22,)": 1, "(,P22": 1, "P22,<": 1, "||,P22": 1, "P22,>": 1, "&,p2": 1, "p2,)": 1, "(,p2": 1, "p2,<": 1, "||,p2": 1, "p2,>": 1, "&,DZ2": 1, "DZ2,)": 1, "(,DZ2": 1, "DZ2,<": 1, "||,DZ2": 1, "DZ2,>": 1, "&,Z2": 1, "Z2,)": 1, "(,Z2": 1, "Z2,<": 1, "||,Z2": 1, "Z2,>": 1, "(,\"Unesite bodove za Mirzu:\\n\"": 1, "\"Unesite bodove za Mirzu:\\n\",)": 1, "&,P13": 1, "P13,)": 1, "(,P13": 1, "P13,<": 1, "||,P13": 1, "P13,>": 1, "&,P23": 1, "P23,)": 1, "(,P23": 1, "P23,<": 1, "||,P23": 1, "P23,>": 1, "&,p3": 1, "p3,)": 1, "(,p3": 1, "p3,<": 1, "||,p3": 1, "p3,>": 1, "&,DZ3": 1, "DZ3,)": 1, "(,DZ3": 1, "DZ3,<": 1, "||,DZ3": 1, "DZ3,>": 1, "&,Z3": 1, "Z3,)": 1, "(,Z3": 1, "Z3,<": 1, "||,Z3": 1, "Z3,>": 1, "{,O1": 1, "=,P11": 1, "P11,+": 1, "+,P21": 1, "P21,+": 1, "+,p1": 1, "p1,+": 1, "+,Z1": 1, "Z1,+": 1, "+,DZ1": 1, "DZ1,;": 1, ";,O2": 1, "=,P12": 1, "P12,+": 1, "+,P22": 1, "P22,+": 1, "+,p2": 1, "p2,+": 1, "+,Z2": 1, "Z2,+": 1, "+,DZ2": 1, "DZ2,;": 1, ";,O3": 1, "=,P13": 1, "P13,+": 1, "+,P23": 1, "P23,+": 1, "+,p3": 1, "p3,+": 1, "+,Z3": 1, "Z3,+": 1, "+,DZ3": 1, "DZ3,;": 1, "(,O1": 34, "O1,<": 43, "<,55": 12, "55,&&": 29, "&&,O2": 83, "O2,<": 42, "&&,O3": 90, "O3,<": 41, "55,)": 19, "(,\"Nijedan student nije polozio.\"": 1, "\"Nijedan student nije polozio.\",)": 1, "else,if": 53, "O3,>=": 50, ">=,55": 36, "(,\"Jedan student je polozio.\"": 3, "\"Jedan student je polozio.\",)": 3, "O2,>=": 50, "O1,>=": 50, "(,\"Dva studenta su polozila.\"": 3, "\"Dva studenta su polozila.\",)": 3, "&&,O1": 64, "<,65": 18, "65,&&": 44, "65,)": 4, "(,\"Sva tri studenta su polozila.\\nSva tri studenta imaju istu ocjenu.\"": 5, "\"Sva tri studenta su polozila.\\nSva tri studenta imaju istu ocjenu.\",)": 5, ">=,65": 30, "<,75": 30, "75,&&": 62, "75,)": 4, ">=,75": 36, "<,85": 39, "85,&&": 59, "85,)": 10, ">=,85": 30, "<,92": 27, "92,&&": 35, "92,)": 10, ">=,92": 18, "O1,<=": 5, "<=,100": 15, "100,&&": 8, "O2,<=": 5, "O3,<=": 5, "100,)": 7, "(,\"Sva tri studenta su polozila.\\nDva od tri studenta imaju istu ocjenu.\"": 24, "\"Sva tri studenta su polozila.\\nDva od tri studenta imaju istu ocjenu.\",)": 24, "(,O2": 14, "(,\"Sva tri studenta su polozila.\\nSvaki student ima razlicitu ocjenu.\"": 18, "\"Sva tri studenta su polozila.\\nSvaki student ima razlicitu ocjenu.\",)": 18, "(,O3": 6, "},}": 1, "},return": 1}