{"#include <stdio.h>": 1, "int": 1, "main": 1, "(": 132, ")": 132, "{": 22, "float": 3, "T1": 5, ",": 36, "T2": 5, "Tp": 5, "Tz": 5, "Tzi": 5, "B1": 5, "B2": 5, "Bp": 5, "Bz": 5, "Bzi": 5, "M1": 5, "M2": 5, "Mp": 5, "Mz": 5, "Mzi": 5, ";": 101, "Ut": 56, "Ub": 56, "Um": 56, "A": 1, "=": 9, "5": 1, "B": 7, "6": 1, "C": 7, "7": 1, "D": 7, "8": 1, "E": 7, "9": 1, "F": 7, "10": 7, "printf": 49, "\"Unesite bodove za Tarika: \\n\"": 1, "\"I parcijalni ispit: \"": 3, "scanf": 15, "\"%g\"": 14, "&": 15, "if": 34, "<": 75, "0": 31, "||": 29, ">": 18, "20": 6, "\"Neispravan broj bodova\"": 15, "return": 16, "}": 22, "\"II parcijalni ispit: \"": 3, "\"Prisustvo: \"": 3, "\"Zadace: \"": 3, "\"Zavrsni ispit: \"": 3, "40": 3, "\"Unesite bodove za Bojana: \\n\"": 1, "\"Unesite bodove za Mirzu:\\n\"": 1, "\"%f\"": 1, "+": 12, "54.99": 3, "&&": 111, "55.00": 18, "\"Jedan student je polozio.\\n\"": 1, "else": 18, ">=": 63, "\"Dva studenta su polozila.\\n\"": 1, "55": 12, "\"Sva tri studenta su polozila.\\n\"": 1, "65": 24, "==": 33, "75": 24, "85": 24, "92": 21, "\"Sva tri studenta imaju istu ocjenu.\\n\"": 6, "\"Dva od tri studenta imaju istu ocjenu.\"": 5, "\"Svaki student ima razlicitu ocjenu.\\n\"": 1, "\"Nijedan student nije polozio.\\n\"": 1}