{"#include <stdio.h>": 1, "#include <stdlib.h>": 1, "int": 4, "main": 1, "(": 464, ")": 464, "{": 23, "float": 2, "PrviParc1": 24, ",": 316, "PrviParc2": 24, "PrviParc3": 24, "DrugiParc1": 24, "DrugiParc2": 24, "DrugiParc3": 24, "Zadace1": 24, "Zadace2": 24, "Zadace3": 24, "Prisustvo1": 24, "Prisustvo2": 24, "Prisustvo3": 24, "Zavrsni1": 23, "Zavrsni2": 25, "Zavrsni3": 24, ";": 374, "BrojBodova1": 40, "BrojBodova2": 40, "BrojBodova3": 40, "scanf": 1, "\"%f %f %f %f %f %f %f %f %f %f %f %f %f %f %f\"": 1, "&": 16, "=": 3, "+": 15, "*": 3, "100": 15, "0.5": 3, "/": 3, "if": 21, "<": 69, "0": 34, "||": 37, ">": 25, "20": 6, "printf": 349, "\"Unesite bodove za Tarika:\\n\"": 19, "\"I parcijalni ispit: Neispravan broj bodova\"": 3, "return": 19, "\"II parcijalni ispit: \"": 54, "\"Prisustvo: \"": 54, "\"Zadace: \"": 54, "\"Zavrsni ispit: \"": 54, "\"Unesite bodove za Bojana:\\n\"": 19, "\"I parcijalni ispit: \"": 54, "\"Unesite bodove za Mirzu:\\n\"": 19, "}": 23, "else": 20, "\"II parcijalni ispit: Neispravan broj bodova\"": 3, "10": 6, "\"Prisustvo: Neispravan broj bodova\"": 3, "\"Zadace: Neispravan broj bodova\"": 3, "40": 3, "\"Zavrsni ispit: Neispravan broj bodova\"": 3, "55": 33, "&&": 86, "\"Nijedan student nije polozio.\\n\"": 1, "\"Sva tri studenta su polozila.\\n\"": 1, ">=": 47, "\"Jedan student je polozio.\\n\"": 1, "\"Dva studenta su polozila.\\n\"": 1, "65": 18, "75": 18, "85": 18, "92": 18, "<=": 3, "\"Sva tri studenta imaju istu ocjenu.\"": 1, "\"Dva od tri studenta imaju istu ocjenu.\"": 1, "\"Svaki student ima razlicitu ocjenu.\"": 1}