{"#include <stdio.h>,int": 1, "int,main": 1, "main,(": 1, "(,)": 1, "),{": 23, "{,double": 1, "double,prvi_par1": 1, "prvi_par1,,": 1, ",,drugi_par1": 1, "drugi_par1,,": 1, ",,prisustvo1": 1, "prisustvo1,,": 1, ",,zadace1": 1, "zadace1,,": 1, ",,zavrsni_ispit1": 1, "zavrsni_ispit1,;": 2, ";,double": 3, "double,prvi_par2": 1, "prvi_par2,,": 1, ",,drugi_par2": 1, "drugi_par2,,": 1, ",,prisustvo2": 1, "prisustvo2,,": 1, ",,zadace2": 1, "zadace2,,": 1, ",,zavrsni_ispit2": 1, "zavrsni_ispit2,;": 2, "double,prvi_par3": 1, "prvi_par3,,": 1, ",,drugi_par3": 1, "drugi_par3,,": 1, ",,prisustvo3": 1, "prisustvo3,,": 1, ",,zadace3": 1, "zadace3,,": 1, ",,zavrsni_ispit3": 1, "zavrsni_ispit3,;": 2, "double,S1": 1, "S1,,": 1, ",,S2": 1, "S2,,": 1, ",,S3": 1, "S3,,": 1, ",,ocj": 1, "ocj,,": 1, ",,ocj1": 1, "ocj1,,": 1, ",,ocj2": 1, "ocj2,,": 1, ",,s1": 1, "s1,,": 1, ",,s2": 1, "s2,,": 1, ",,s3": 1, "s3,;": 1, ";,printf": 4, "printf,(": 40, "(,\"Unesite bodove za Tarika:\\n\"": 1, "\"Unesite bodove za Tarika:\\n\",)": 1, "),;": 55, "(,\"I parcijalni ispit: \"": 3, "\"I parcijalni ispit: \",)": 3, ";,scanf": 15, "scanf,(": 15, "(,\"%lf\"": 15, "\"%lf\",,": 15, ",,&": 15, "&,prvi_par1": 1, "prvi_par1,)": 1, ";,if": 20, "if,(": 40, "(,prvi_par1": 1, "prvi_par1,<": 1, "<,0": 15, "0,||": 15, "||,prvi_par1": 1, "prvi_par1,>": 1, ">,20": 6, "20,)": 6, "{,printf": 22, "(,\"Neispravan broj bodova\"": 15, "\"Neispravan broj bodova\",)": 15, ";,return": 15, "return,0": 16, "0,;": 16, ";,}": 22, "},printf": 14, "(,\"II parcijalni ispit: \"": 3, "\"II parcijalni ispit: \",)": 3, "&,drugi_par1": 1, "drugi_par1,)": 1, "(,drugi_par1": 1, "drugi_par1,<": 1, "||,drugi_par1": 1, "drugi_par1,>": 1, "(,\"Prisustvo: \"": 3, "\"Prisustvo: \",)": 3, "&,prisustvo1": 1, "prisustvo1,)": 1, "(,prisustvo1": 1, "prisustvo1,<": 1, "||,prisustvo1": 1, "prisustvo1,>": 1, ">,10": 6, "10,)": 6, "(,\"Zadace: \"": 3, "\"Zadace: \",)": 3, "&,zadace1": 1, "zadace1,)": 1, "(,zadace1": 1, "zadace1,<": 1, "||,zadace1": 1, "zadace1,>": 1, "(,\"Zavrsni ispit: \"": 3, "\"Zavrsni ispit: \",)": 3, "&,zavrsni_ispit1": 1, "zavrsni_ispit1,)": 1, "(,zavrsni_ispit1": 1, "zavrsni_ispit1,<": 1, "||,zavrsni_ispit1": 1, "zavrsni_ispit1,>": 1, ">,40": 3, "40,)": 3, "(,\"Unesite bodove za Bojana:\\n\"": 1, "\"Unesite bodove za Bojana:\\n\",)": 1, "&,prvi_par2": 1, "prvi_par2,)": 1, "(,prvi_par2": 1, "prvi_par2,<": 1, "||,prvi_par2": 1, "prvi_par2,>": 1, "&,drugi_par2": 1, "drugi_par2,)": 1, "(,drugi_par2": 1, "drugi_par2,<": 1, "||,drugi_par2": 1, "drugi_par2,>": 1, "&,prisustvo2": 1, "prisustvo2,)": 1, "(,prisustvo2": 1, "prisustvo2,<": 1, "||,prisustvo2": 1, "prisustvo2,>": 1, "&,zadace2": 1, "zadace2,)": 1, "(,zadace2": 1, "zadace2,<": 1, "||,zadace2": 1, "zadace2,>": 1, "&,zavrsni_ispit2": 1, "zavrsni_ispit2,)": 1, "(,zavrsni_ispit2": 1, "zavrsni_ispit2,<": 1, "||,zavrsni_ispit2": 1, "zavrsni_ispit2,>": 1, "(,\"Unesite bodove za Mirzu:\\n\"": 1, "\"Unesite bodove za Mirzu:\\n\",)": 1, "&,prvi_par3": 1, "prvi_par3,)": 1, "(,prvi_par3": 1, "prvi_par3,<": 1, "||,prvi_par3": 1, "prvi_par3,>": 1, "&,drugi_par3": 1, "drugi_par3,)": 1, "(,drugi_par3": 1, "drugi_par3,<": 1, "||,drugi_par3": 1, "drugi_par3,>": 1, "&,prisustvo3": 1, "prisustvo3,)": 1, "(,prisustvo3": 1, "prisustvo3,<": 1, "||,prisustvo3": 1, "prisustvo3,>": 1, "&,zadace3": 1, "zadace3,)": 1, "(,zadace3": 1, "zadace3,<": 1, "||,zadace3": 1, "zadace3,>": 1, "&,zavrsni_ispit3": 1, "zavrsni_ispit3,)": 1, "(,zavrsni_ispit3": 1, "zavrsni_ispit3,<": 1, "||,zavrsni_ispit3": 1, "zavrsni_ispit3,>": 1, "},S1": 1, "S1,=": 1, "=,prvi_par1": 1, "prvi_par1,+": 1, "+,drugi_par1": 1, "drugi_par1,+": 1, "+,prisustvo1": 1, "prisustvo1,+": 1, "+,zadace1": 1, "zadace1,+": 1, "+,zavrsni_ispit1": 1, ";,S2": 1, "S2,=": 1, "=,prvi_par2": 1, "prvi_par2,+": 1, "+,drugi_par2": 1, "drugi_par2,+": 1, "+,prisustvo2": 1, "prisustvo2,+": 1, "+,zadace2": 1, "zadace2,+": 1, "+,zavrsni_ispit2": 1, ";,S3": 1, "S3,=": 1, "=,prvi_par3": 1, "prvi_par3,+": 1, "+,drugi_par3": 1, "drugi_par3,+": 1, "+,prisustvo3": 1, "prisustvo3,+": 1, "+,zadace3": 1, "zadace3,+": 1, "+,zavrsni_ispit3": 1, "(,S1": 6, "S1,<": 5, "<,55": 3, "55,)": 3, "),ocj": 6, "ocj,=": 6, "=,5": 3, "5,;": 3, ";,else": 15, "else,if": 20, "S1,>=": 5, ">=,55": 3, "55,&&": 3, "&&,S1": 5, "<,65": 3, "65,)": 3, "=,6": 3, "6,;": 3, ">=,65": 3, "65,&&": 3, "<,75": 3, "75,)": 3, "=,7": 3, "7,;": 3, ">=,75": 3, "75,&&": 3, "<,85": 3, "85,)": 3, "=,8": 3, "8,;": 3, ">=,85": 3, "85,&&": 3, "<,92": 3, "92,)": 3, "=,9": 3, "9,;": 3, ">=,92": 3, "92,&&": 3, "S1,<=": 1, "<=,100": 3, "100,)": 3, "=,10": 3, "10,;": 3, "(,S2": 6, "S2,<": 5, "),ocj1": 6, "ocj1,=": 6, "S2,>=": 5, "&&,S2": 5, "S2,<=": 1, "(,S3": 6, "S3,<": 5, "),ocj2": 6, "ocj2,=": 6, "S3,>=": 5, "&&,S3": 5, "S3,<=": 1, ";,s1": 1, "s1,=": 1, "=,ocj": 1, "ocj,;": 1, ";,s2": 1, "s2,=": 1, "=,ocj1": 1, "ocj1,;": 1, ";,s3": 1, "s3,=": 1, "=,ocj2": 1, "ocj2,;": 1, "(,s1": 7, "s1,==": 8, "==,5": 12, "5,&&": 16, "&&,s2": 9, "s2,==": 5, "&&,s3": 9, "s3,==": 4, "5,)": 4, "(,\"Nijedan student nije polozio.\\n\"": 1, "\"Nijedan student nije polozio.\\n\",)": 1, "},else": 5, "s3,>": 4, ">,5": 12, "5,||": 4, "||,s1": 5, "s2,>": 4, "s1,>": 4, "(,\"Jedan student je polozio.\\n\"": 1, "\"Jedan student je polozio.\\n\",)": 1, "(,\"Dva studenta su polozila. \\n\"": 1, "\"Dva studenta su polozila. \\n\",)": 1, "(,\"Sva tri studenta su polozila.\\n\"": 1, "\"Sva tri studenta su polozila.\\n\",)": 1, "==,s2": 2, "s2,&&": 2, "&&,s1": 1, "==,s3": 3, "s3,)": 2, "(,\"Sva tri studenta imaju istu ocjenu.\\n\"": 1, "\"Sva tri studenta imaju istu ocjenu.\\n\",)": 1, "s2,||": 1, "s3,||": 1, "||,s2": 1, "(,\"Dva od tri studenta imaju istu ocjenu.\\n\"": 1, "\"Dva od tri studenta imaju istu ocjenu.\\n\",)": 1, "s1,!=": 1, "!=,s2": 1, "s2,!=": 1, "!=,s3": 1, "s3,&&": 1, "s3,!=": 1, "!=,s1": 1, "s1,)": 1, "(,\"Svaki student ima razlicitu ocjenu.\\n\"": 1, "\"Svaki student ima razlicitu ocjenu.\\n\",)": 1, "},}": 1, "},return": 1}