{"#include <stdio.h>,int": 1, "int,main": 1, "main,(": 1, "(,)": 1, "),{": 20, "{,double": 1, "double,ppt": 1, "ppt,,": 1, ",,dpt": 1, "dpt,,": 1, ",,pt": 1, "pt,,": 1, ",,zt": 1, "zt,,": 1, ",,zit": 1, "zit,,": 1, ",,ppb": 1, "ppb,,": 1, ",,dpb": 1, "dpb,,": 1, ",,pb": 1, "pb,,": 1, ",,zb": 1, "zb,,": 1, ",,zib": 1, "zib,,": 1, ",,ppm": 1, "ppm,,": 1, ",,dpm": 1, "dpm,,": 1, ",,pm": 1, "pm,,": 1, ",,zm": 1, "zm,,": 1, ",,zim": 1, "zim,,": 1, ",,ubb": 1, "ubb,,": 1, ",,ubm": 1, "ubm,,": 1, ",,ubt": 1, "ubt,;": 1, ";,printf": 4, "printf,(": 57, "(,\"Unesite bodove za Tarika:\\n\"": 1, "\"Unesite bodove za Tarika:\\n\",)": 1, "),;": 72, "(,\"I parcijalni ispit: \"": 3, "\"I parcijalni ispit: \",)": 3, ";,scanf": 15, "scanf,(": 15, "(,\"%lf\"": 15, "\"%lf\",,": 15, ",,&": 15, "&,ppt": 1, "ppt,)": 1, ";,if": 17, "if,(": 37, "(,ppt": 1, "ppt,<": 1, "<,0": 15, "0,||": 15, "||,ppt": 1, "ppt,>": 1, ">,20": 6, "20,)": 6, "{,printf": 20, "(,\"Neispravan broj bodova\"": 14, "\"Neispravan broj bodova\",)": 14, ";,return": 15, "return,0": 16, "0,;": 16, ";,}": 21, "},printf": 14, "(,\"II parcijalni ispit: \"": 3, "\"II parcijalni ispit: \",)": 3, "&,dpt": 1, "dpt,)": 1, "(,dpt": 1, "dpt,<": 1, "||,dpt": 1, "dpt,>": 1, "(,\"Prisustvo: \"": 3, "\"Prisustvo: \",)": 3, "&,pt": 1, "pt,)": 1, "(,pt": 1, "pt,<": 1, "||,pt": 1, "pt,>": 1, ">,10": 6, "10,)": 6, "(,\"Zadace: \"": 3, "\"Zadace: \",)": 3, "&,zt": 1, "zt,)": 1, "(,zt": 1, "zt,<": 1, "||,zt": 1, "zt,>": 1, "(,\"Zavrsni ispit: \"": 3, "\"Zavrsni ispit: \",)": 3, "&,zit": 1, "zit,)": 1, "(,zit": 1, "zit,<": 1, "||,zit": 1, "zit,>": 1, ">,40": 3, "40,)": 3, "(,\"Unesite bodove za Bojana:\\n\"": 1, "\"Unesite bodove za Bojana:\\n\",)": 1, "&,ppb": 1, "ppb,)": 1, "(,ppb": 1, "ppb,<": 1, "||,ppb": 1, "ppb,>": 1, "&,dpb": 1, "dpb,)": 1, "(,dpb": 1, "dpb,<": 1, "||,dpb": 1, "dpb,>": 1, "&,pb": 1, "pb,)": 1, "(,pb": 1, "pb,<": 1, "||,pb": 1, "pb,>": 1, "&,zb": 1, "zb,)": 1, "(,zb": 1, "zb,<": 1, "||,zb": 1, "zb,>": 1, "&,zib": 1, "zib,)": 1, "(,zib": 1, "zib,<": 1, "||,zib": 1, "zib,>": 1, "(,\"Unesite bodove za Mirzu:\\n\"": 1, "\"Unesite bodove za Mirzu:\\n\",)": 1, "&,ppm": 1, "ppm,)": 1, "(,ppm": 1, "ppm,<": 1, "||,ppm": 1, "ppm,>": 1, "(,\"Neispravan  broj bodova\"": 1, "\"Neispravan  broj bodova\",)": 1, "&,dpm": 1, "dpm,)": 1, "(,dpm": 1, "dpm,<": 1, "||,dpm": 1, "dpm,>": 1, "&,pm": 1, "pm,)": 1, "(,pm": 1, "pm,<": 1, "||,pm": 1, "pm,>": 1, "&,zm": 1, "zm,)": 1, "(,zm": 1, "zm,<": 1, "||,zm": 1, "zm,>": 1, "&,zim": 1, "zim,)": 1, "(,zim": 1, "zim,<": 1, "||,zim": 1, "zim,>": 1, "},ubt": 1, "ubt,=": 1, "=,ppt": 1, "ppt,+": 1, "+,dpt": 1, "dpt,+": 1, "+,zt": 1, "zt,+": 1, "+,zit": 1, "zit,+": 1, "+,pt": 1, "pt,;": 1, ";,ubm": 1, "ubm,=": 1, "=,ppm": 1, "ppm,+": 1, "+,dpm": 1, "dpm,+": 1, "+,zm": 1, "zm,+": 1, "+,zim": 1, "zim,+": 1, "+,pm": 1, "pm,;": 1, ";,ubb": 1, "ubb,=": 1, "=,ppb": 1, "ppb,+": 1, "+,dpb": 1, "dpb,+": 1, "+,zb": 1, "zb,+": 1, "+,zib": 1, "zib,+": 1, "+,pb": 1, "pb,;": 1, "(,ubb": 7, "ubb,<": 19, "<,55": 9, "55,&&": 16, "&&,ubm": 24, "ubm,<": 19, "&&,ubt": 32, "ubt,<": 19, "55,)": 5, "(,\"Nijedan student nije polozio.\\n\"": 1, "\"Nijedan student nije polozio.\\n\",)": 1, "},else": 4, "else,if": 20, "(,(": 4, "ubt,>=": 20, ">=,55": 12, "),||": 3, "||,(": 3, "ubm,>=": 20, "ubb,>=": 20, "),)": 4, "),printf": 18, "(,\"Jedan student je polozio.\\n\"": 1, "\"Jedan student je polozio.\\n\",)": 1, ";,else": 18, "(,\"Sva tri studenta su polozila.\\n\"": 1, "\"Sva tri studenta su polozila.\\n\",)": 1, "(,ubm": 15, "<,65": 12, "65,&&": 20, "&&,ubb": 32, "65,)": 4, ">=,92": 12, "92,&&": 19, "92,)": 5, "(,\"Sva tri studenta imaju istu ocjenu.\\n\"": 4, "\"Sva tri studenta imaju istu ocjenu.\\n\",)": 4, ">=,85": 12, "85,&&": 15, "<,92": 12, ">=,75": 12, "75,&&": 18, "<,85": 12, "85,)": 9, "),&&": 4, "&&,(": 4, "(,ubt": 7, ">=,65": 12, "<,75": 12, "75,)": 6, "(,\"Dva od tri studenta imaju istu ocjenu.\\n\"": 15, "\"Dva od tri studenta imaju istu ocjenu.\\n\",)": 15, "else,printf": 1, "(,\"Svaki student ima razlicitu ocjenu.\"": 1, "\"Svaki student ima razlicitu ocjenu.\",)": 1, "else,{": 1, "(,\"Dva studenta su polozila.\"": 1, "\"Dva studenta su polozila.\",)": 1, "},return": 1}