{"#include <stdio.h>,int,main": 1, "int,main,(": 1, "main,(,)": 1, "(,),{": 1, "),{,double": 1, "{,double,tarik": 1, "double,tarik,,": 1, "tarik,,,bojan": 1, ",,bojan,,": 1, "bojan,,,mirza": 1, ",,mirza,;": 1, "mirza,;,double": 1, ";,double,I_par_t": 1, "double,I_par_t,,": 1, "I_par_t,,,II_par_t": 1, ",,II_par_t,,": 1, "II_par_t,,,zavrsni_t": 1, ",,zavrsni_t,,": 1, "zavrsni_t,,,zadaca_t": 1, ",,zadaca_t,,": 1, "zadaca_t,,,prisustvo_t": 1, ",,prisustvo_t,,": 1, "prisustvo_t,,,I_par_b": 1, ",,I_par_b,,": 1, "I_par_b,,,II_par_b": 1, ",,II_par_b,,": 1, "II_par_b,,,zavrsni_b": 1, ",,zavrsni_b,,": 1, "zavrsni_b,,,zadaca_b": 1, ",,zadaca_b,,": 1, "zadaca_b,,,prisustvo_b": 1, ",,prisustvo_b,,": 1, "prisustvo_b,,,I_par_m": 1, ",,I_par_m,,": 1, "I_par_m,,,II_par_m": 1, ",,II_par_m,,": 1, "II_par_m,,,zavrsni_m": 1, ",,zavrsni_m,,": 1, "zavrsni_m,,,zadaca_m": 1, ",,zadaca_m,,": 1, "zadaca_m,,,prisustvo_m": 1, ",,prisustvo_m,;": 1, "prisustvo_m,;,printf": 1, ";,printf,(": 4, "printf,(,\"Unesite bodove za Tarika:\\n\"": 1, "(,\"Unesite bodove za Tarika:\\n\",)": 1, "\"Unesite bodove za Tarika:\\n\",),;": 1, "),;,printf": 3, "printf,(,\"I parcijalni ispit: \"": 3, "(,\"I parcijalni ispit: \",)": 3, "\"I parcijalni ispit: \",),;": 3, "),;,scanf": 15, ";,scanf,(": 15, "scanf,(,\"%lf\"": 15, "(,\"%lf\",,": 15, "\"%lf\",,,&": 15, ",,&,I_par_t": 1, "&,I_par_t,)": 1, "I_par_t,),;": 1, "),;,if": 21, ";,if,(": 40, "if,(,I_par_t": 1, "(,I_par_t,>": 1, "I_par_t,>,20": 1, ">,20,||": 6, "20,||,I_par_t": 1, "||,I_par_t,<": 1, "I_par_t,<,0": 1, "<,0,)": 15, "0,),{": 15, "),{,printf": 15, "{,printf,(": 15, "printf,(,\"Neispravan broj bodova\"": 15, "(,\"Neispravan broj bodova\",)": 15, "\"Neispravan broj bodova\",),;": 15, "),;,return": 16, ";,return,0": 16, "return,0,;": 16, "0,;,}": 16, ";,},printf": 14, "},printf,(": 14, "printf,(,\"II parcijalni ispit: \"": 3, "(,\"II parcijalni ispit: \",)": 3, "\"II parcijalni ispit: \",),;": 3, ",,&,II_par_t": 1, "&,II_par_t,)": 1, "II_par_t,),;": 1, "if,(,II_par_t": 1, "(,II_par_t,>": 1, "II_par_t,>,20": 1, "20,||,II_par_t": 1, "||,II_par_t,<": 1, "II_par_t,<,0": 1, "printf,(,\"Prisustvo: \"": 3, "(,\"Prisustvo: \",)": 3, "\"Prisustvo: \",),;": 3, ",,&,prisustvo_t": 1, "&,prisustvo_t,)": 1, "prisustvo_t,),;": 1, "if,(,prisustvo_t": 1, "(,prisustvo_t,>": 1, "prisustvo_t,>,10": 1, ">,10,||": 6, "10,||,prisustvo_t": 1, "||,prisustvo_t,<": 1, "prisustvo_t,<,0": 1, "printf,(,\"Zadace: \"": 3, "(,\"Zadace: \",)": 3, "\"Zadace: \",),;": 3, ",,&,zadaca_t": 1, "&,zadaca_t,)": 1, "zadaca_t,),;": 1, "if,(,zadaca_t": 1, "(,zadaca_t,>": 1, "zadaca_t,>,10": 1, "10,||,zadaca_t": 1, "||,zadaca_t,<": 1, "zadaca_t,<,0": 1, "printf,(,\"Zavrsni ispit: \"": 3, "(,\"Zavrsni ispit: \",)": 3, "\"Zavrsni ispit: \",),;": 3, ",,&,zavrsni_t": 1, "&,zavrsni_t,)": 1, "zavrsni_t,),;": 1, "if,(,zavrsni_t": 1, "(,zavrsni_t,>": 1, "zavrsni_t,>,40": 1, ">,40,||": 3, "40,||,zavrsni_t": 1, "||,zavrsni_t,<": 1, "zavrsni_t,<,0": 1, "printf,(,\"Unesite bodove za Bojana:\\n\"": 1, "(,\"Unesite bodove za Bojana:\\n\",)": 1, "\"Unesite bodove za Bojana:\\n\",),;": 1, ",,&,I_par_b": 1, "&,I_par_b,)": 1, "I_par_b,),;": 1, "if,(,I_par_b": 1, "(,I_par_b,>": 1, "I_par_b,>,20": 1, "20,||,I_par_b": 1, "||,I_par_b,<": 1, "I_par_b,<,0": 1, ",,&,II_par_b": 1, "&,II_par_b,)": 1, "II_par_b,),;": 1, "if,(,II_par_b": 1, "(,II_par_b,>": 1, "II_par_b,>,20": 1, "20,||,II_par_b": 1, "||,II_par_b,<": 1, "II_par_b,<,0": 1, ",,&,prisustvo_b": 1, "&,prisustvo_b,)": 1, "prisustvo_b,),;": 1, "if,(,prisustvo_b": 1, "(,prisustvo_b,>": 1, "prisustvo_b,>,10": 1, "10,||,prisustvo_b": 1, "||,prisustvo_b,<": 1, "prisustvo_b,<,0": 1, ",,&,zadaca_b": 1, "&,zadaca_b,)": 1, "zadaca_b,),;": 1, "if,(,zadaca_b": 1, "(,zadaca_b,>": 1, "zadaca_b,>,10": 1, "10,||,zadaca_b": 1, "||,zadaca_b,<": 1, "zadaca_b,<,0": 1, ",,&,zavrsni_b": 1, "&,zavrsni_b,)": 1, "zavrsni_b,),;": 1, "if,(,zavrsni_b": 1, "(,zavrsni_b,>": 1, "zavrsni_b,>,40": 1, "40,||,zavrsni_b": 1, "||,zavrsni_b,<": 1, "zavrsni_b,<,0": 1, "printf,(,\"Unesite bodove za Mirzu:\\n\"": 1, "(,\"Unesite bodove za Mirzu:\\n\",)": 1, "\"Unesite bodove za Mirzu:\\n\",),;": 1, ",,&,I_par_m": 1, "&,I_par_m,)": 1, "I_par_m,),;": 1, "if,(,I_par_m": 1, "(,I_par_m,>": 1, "I_par_m,>,20": 1, "20,||,I_par_m": 1, "||,I_par_m,<": 1, "I_par_m,<,0": 1, ",,&,II_par_m": 1, "&,II_par_m,)": 1, "II_par_m,),;": 1, "if,(,II_par_m": 1, "(,II_par_m,>": 1, "II_par_m,>,20": 1, "20,||,II_par_m": 1, "||,II_par_m,<": 1, "II_par_m,<,0": 1, ",,&,prisustvo_m": 1, "&,prisustvo_m,)": 1, "prisustvo_m,),;": 1, "if,(,prisustvo_m": 1, "(,prisustvo_m,>": 1, "prisustvo_m,>,10": 1, "10,||,prisustvo_m": 1, "||,prisustvo_m,<": 1, "prisustvo_m,<,0": 1, ",,&,zadaca_m": 1, "&,zadaca_m,)": 1, "zadaca_m,),;": 1, "if,(,zadaca_m": 1, "(,zadaca_m,>": 1, "zadaca_m,>,10": 1, "10,||,zadaca_m": 1, "||,zadaca_m,<": 1, "zadaca_m,<,0": 1, ",,&,zavrsni_m": 1, "&,zavrsni_m,)": 1, "zavrsni_m,),;": 1, "if,(,zavrsni_m": 1, "(,zavrsni_m,>": 1, "zavrsni_m,>,40": 1, "40,||,zavrsni_m": 1, "||,zavrsni_m,<": 1, "zavrsni_m,<,0": 1, ";,},tarik": 1, "},tarik,=": 1, "tarik,=,I_par_t": 1, "=,I_par_t,+": 1, "I_par_t,+,II_par_t": 1, "+,II_par_t,+": 1, "II_par_t,+,prisustvo_t": 1, "+,prisustvo_t,+": 1, "prisustvo_t,+,zadaca_t": 1, "+,zadaca_t,+": 1, "zadaca_t,+,zavrsni_t": 1, "+,zavrsni_t,;": 1, "zavrsni_t,;,bojan": 1, ";,bojan,=": 1, "bojan,=,I_par_b": 1, "=,I_par_b,+": 1, "I_par_b,+,II_par_b": 1, "+,II_par_b,+": 1, "II_par_b,+,prisustvo_b": 1, "+,prisustvo_b,+": 1, "prisustvo_b,+,zadaca_b": 1, "+,zadaca_b,+": 1, "zadaca_b,+,zavrsni_b": 1, "+,zavrsni_b,;": 1, "zavrsni_b,;,mirza": 1, ";,mirza,=": 1, "mirza,=,I_par_m": 1, "=,I_par_m,+": 1, "I_par_m,+,II_par_m": 1, "+,II_par_m,+": 1, "II_par_m,+,prisustvo_m": 1, "+,prisustvo_m,+": 1, "prisustvo_m,+,zadaca_m": 1, "+,zadaca_m,+": 1, "zadaca_m,+,zavrsni_m": 1, "+,zavrsni_m,;": 1, "zavrsni_m,;,if": 1, "if,(,tarik": 9, "(,tarik,<": 1, "tarik,<,55": 1, "<,55,)": 3, "55,),tarik": 1, "),tarik,=": 6, "tarik,=,0": 1, "=,0,;": 3, "0,;,if": 3, "(,tarik,>=": 8, "tarik,>=,55": 1, ">=,55,&&": 3, "55,&&,tarik": 1, "&&,tarik,<": 4, "tarik,<,65": 1, "<,65,)": 3, "65,),tarik": 1, "tarik,=,6": 1, "=,6,;": 3, "6,;,if": 3, "tarik,>=,65": 1, ">=,65,&&": 3, "65,&&,tarik": 1, "tarik,<,75": 1, "<,75,)": 3, "75,),tarik": 1, "tarik,=,7": 1, "=,7,;": 3, "7,;,if": 3, "tarik,>=,75": 1, ">=,75,&&": 3, "75,&&,tarik": 1, "tarik,<,85": 1, "<,85,)": 3, "85,),tarik": 1, "tarik,=,8": 1, "=,8,;": 3, "8,;,if": 3, "tarik,>=,85": 1, ">=,85,&&": 3, "85,&&,tarik": 1, "tarik,<,92": 1, "<,92,)": 3, "92,),tarik": 2, "tarik,=,9": 1, "=,9,;": 3, "9,;,if": 3, "tarik,>=,92": 1, ">=,92,)": 3, "tarik,=,10": 1, "=,10,;": 3, "10,;,if": 3, "if,(,bojan": 6, "(,bojan,<": 1, "bojan,<,55": 1, "55,),bojan": 1, "),bojan,=": 6, "bojan,=,0": 1, "(,bojan,>=": 5, "bojan,>=,55": 1, "55,&&,bojan": 1, "&&,bojan,<": 4, "bojan,<,65": 1, "65,),bojan": 1, "bojan,=,6": 1, "bojan,>=,65": 1, "65,&&,bojan": 1, "bojan,<,75": 1, "75,),bojan": 1, "bojan,=,7": 1, "bojan,>=,75": 1, "75,&&,bojan": 1, "bojan,<,85": 1, "85,),bojan": 1, "bojan,=,8": 1, "bojan,>=,85": 1, "85,&&,bojan": 1, "bojan,<,92": 1, "92,),bojan": 2, "bojan,=,9": 1, "bojan,>=,92": 1, "bojan,=,10": 1, "if,(,mirza": 6, "(,mirza,<": 1, "mirza,<,55": 1, "55,),mirza": 1, "),mirza,=": 6, "mirza,=,0": 1, "(,mirza,>=": 6, "mirza,>=,55": 1, "55,&&,mirza": 1, "&&,mirza,<": 4, "mirza,<,65": 1, "65,),mirza": 1, "mirza,=,6": 1, "mirza,>=,65": 1, "65,&&,mirza": 1, "mirza,<,75": 1, "75,),mirza": 1, "mirza,=,7": 1, "mirza,>=,75": 1, "75,&&,mirza": 1, "mirza,<,85": 1, "85,),mirza": 1, "mirza,=,8": 1, "mirza,>=,85": 1, "85,&&,mirza": 1, "mirza,<,92": 1, "92,),mirza": 2, "mirza,=,9": 1, "mirza,>=,92": 1, "mirza,=,10": 1, "(,tarik,==": 6, "tarik,==,0": 4, "==,0,&&": 6, "0,&&,mirza": 7, "&&,mirza,==": 4, "mirza,==,0": 4, "0,&&,bojan": 7, "&&,bojan,==": 5, "bojan,==,0": 4, "==,0,)": 6, "0,),printf": 3, "),printf,(": 7, "printf,(,\"Nijedan student nije polozio.\\n\"": 1, "(,\"Nijedan student nije polozio.\\n\",)": 1, "\"Nijedan student nije polozio.\\n\",),;": 1, "if,(,(": 4, "(,(,tarik": 4, "tarik,>=,6": 3, ">=,6,&&": 8, "6,&&,mirza": 3, "0,),||": 4, "),||,(": 6, "||,(,tarik": 4, "&&,mirza,>=": 2, "mirza,>=,6": 3, "6,&&,bojan": 4, "&&,bojan,>=": 3, "bojan,>=,6": 3, ">=,6,)": 1, "6,),)": 1, "),),printf": 4, "printf,(,\"Jedan student je polozio.\\n\"": 1, "(,\"Jedan student je polozio.\\n\",)": 1, "\"Jedan student je polozio.\\n\",),;": 1, "||,(,mirza": 2, "6,&&,tarik": 1, "&&,tarik,==": 1, "0,),)": 3, "printf,(,\"Dva studenta su polozila.\\n\"": 1, "(,\"Dva studenta su polozila.\\n\",)": 1, "\"Dva studenta su polozila.\\n\",),;": 1, "(,tarik,!=": 4, "tarik,!=,0": 4, "!=,0,&&": 8, "&&,bojan,!=": 6, "bojan,!=,0": 4, "&&,mirza,!=": 6, "mirza,!=,0": 4, "!=,0,)": 4, "printf,(,\"Sva tri studenta su polozila.\\n\"": 1, "(,\"Sva tri studenta su polozila.\\n\",)": 1, "\"Sva tri studenta su polozila.\\n\",),;": 1, "tarik,!=,bojan": 1, "!=,bojan,&&": 1, "bojan,&&,bojan": 3, "bojan,!=,mirza": 1, "!=,mirza,&&": 1, "mirza,&&,tarik": 1, "&&,tarik,!=": 1, "printf,(,\"Svaki student ima razlicitu ocjenu.\\n\"": 1, "(,\"Svaki student ima razlicitu ocjenu.\\n\",)": 1, "\"Svaki student ima razlicitu ocjenu.\\n\",),;": 1, "(,(,(": 1, "tarik,==,mirza": 1, "==,mirza,&&": 1, "mirza,&&,mirza": 1, "mirza,!=,bojan": 1, "!=,bojan,)": 1, "bojan,),||": 1, "(,mirza,==": 1, "mirza,==,bojan": 1, "==,bojan,&&": 3, "bojan,!=,tarik": 1, "!=,tarik,)": 2, "tarik,),||": 1, "tarik,==,bojan": 2, "bojan,&&,mirza": 1, "mirza,!=,tarik": 1, "tarik,),)": 1, "),),&&": 1, "),&&,(": 2, "&&,(,tarik": 2, "printf,(,\"Dva od tri studenta imaju istu ocjenu.\\n\"": 1, "(,\"Dva od tri studenta imaju istu ocjenu.\\n\",)": 1, "\"Dva od tri studenta imaju istu ocjenu.\\n\",),;": 1, "bojan,==,mirza": 1, "==,mirza,)": 1, "mirza,),&&": 1, "printf,(,\"Sva tri studenta imaju istu ocjenu.\\n\"": 1, "(,\"Sva tri studenta imaju istu ocjenu.\\n\",)": 1, "\"Sva tri studenta imaju istu ocjenu.\\n\",),;": 1}