{"import,java": 1, "java,.": 1, ".,util": 1, "util,.": 1, ".,Scanner": 1, "Scanner,;": 1, ";,public": 1, "public,class": 1, "class,T07": 1, "T07,{": 1, "{,public": 1, "public,static": 2, "static,void": 1, "void,main": 1, "main,(": 1, "(,String": 1, "String,[": 1, "[,]": 5, "],args": 1, "args,)": 1, "),{": 5, "{,Scanner": 1, "Scanner,sc": 1, "sc,=": 1, "=,new": 2, "new,Scanner": 1, "Scanner,(": 1, "(,System": 1, "System,.": 3, ".,in": 1, "in,)": 1, "),;": 5, ";,double": 1, "double,[": 3, "],[": 5, "],matrix": 1, "matrix,=": 1, "new,double": 1, "[,4": 2, "4,]": 2, "],;": 2, ";,System": 2, ".,out": 2, "out,.": 2, ".,println": 2, "println,(": 2, "(,\"Enter a 4-by-4 matrix row to row : \"": 1, "\"Enter a 4-by-4 matrix row to row : \",)": 1, ";,for": 2, "for,(": 3, "(,int": 3, "int,i": 2, "i,=": 2, "=,0": 4, "0,;": 4, ";,i": 4, "i,<": 2, "<,4": 3, "4,;": 3, "i,++": 2, "++,)": 3, "{,for": 1, "int,j": 1, "j,=": 1, ";,j": 2, "j,<": 1, "j,++": 1, "{,matrix": 1, "matrix,[": 1, "[,i": 3, "i,]": 3, "[,j": 1, "j,]": 1, "],=": 1, "=,sc": 1, "sc,.": 1, ".,nextDouble": 1, "nextDouble,(": 1, "(,)": 1, ";,}": 4, "},}": 2, "},double": 1, "double,result": 2, "result,=": 2, "=,sumMajorDiagonal": 1, "sumMajorDiagonal,(": 2, "(,matrix": 1, "matrix,)": 1, "(,\"Sum of the element in the major diagonal is \"": 1, "\"Sum of the element in the major diagonal is \",+": 1, "+,result": 1, "result,)": 1, "},public": 1, "static,double": 1, "double,sumMajorDiagonal": 1, "(,double": 1, "],m": 1, "m,)": 1, "{,double": 1, "{,result": 1, "result,+=": 1, "+=,m": 1, "m,[": 1, "},return": 1, "return,result": 1, "result,;": 1}